{
  "projectId": "gen-lang-client-0559599286",
  "appId": "1:23057012653:web:f99038e42e2a22a17db324",
  "apiKey": "AIzaSyDngPhWWoMMoEMZlRhs6EzZaBLRVBTlzfg",
  "authDomain": "gen-lang-client-0559599286.firebaseapp.com",
  "firestoreDatabaseId": "ai-studio-pdfquizgenerator-101ab23f-c3cf-4a2d-ba1e-56b5aea3eb14",
  "storageBucket": "gen-lang-client-0559599286.firebasestorage.app",
  "messagingSenderId": "23057012653",
  "measurementId": "",
  "oAuthClientId": "23057012653-h3iea7gt646ams36gegacac64ipk4vpe.apps.googleusercontent.com",
  "recaptchaSiteKey": ""
}